LICENSE
MANIFEST.in
README.md
requirements.txt
setup.py
calib/__init__.py
calib/__main__.py
calib/manager.py
calib/openssl.config.template
calib/version.py
calib.egg-info/PKG-INFO
calib.egg-info/SOURCES.txt
calib.egg-info/dependency_links.txt
calib.egg-info/requires.txt
calib.egg-info/top_level.txt