Metadata-Version: 1.1
Name: calib
Version: 0.1.1
Summary: Certificate Authority Lib & Tools
Home-page: https://github.com/lipixun/pyca
Author: lipixun
Author-email: lipixun@outlook.com
License: LICENSE
Keywords: python,ca,certificate,openssl
Platform: UNKNOWN
Classifier: Development Status :: 5 - Production/Stable
Classifier: License :: OSI Approved :: GNU General Public License v2 (GPLv2)
Classifier: Intended Audience :: Developers
Classifier: Operating System :: POSIX
Classifier: Topic :: Internet
Classifier: Topic :: Software Development :: Libraries
Classifier: Topic :: Software Development :: Libraries :: Python Modules
Classifier: Programming Language :: Python
Classifier: Programming Language :: Python :: 2.7
